sloth_ci/__init__.py
sloth_ci/bed.py
sloth_ci/cli.py
sloth_ci/sloth.py
sloth_ci_ext_api/__init__.py
sloth_ci_ext_api/bed.py
sloth_ci_ext_api/cli.py
sloth_ci_ext_db/__init__.py
sloth_ci_ext_db/builds.py
sloth_ci_ext_db/logs.py
sloth_ci_ext_db/util.py
sloth_ci-2.2.1.dist-info/entry_points.txt
sloth_ci-2.2.1.dist-info/LICENSE
sloth_ci-2.2.1.dist-info/WHEEL
sloth_ci-2.2.1.dist-info/METADATA
sloth_ci-2.2.1.dist-info/RECORD
